LICENSE.md
README.md
setup.py
sib_api_v3_sdk/__init__.py
sib_api_v3_sdk/api_client.py
sib_api_v3_sdk/configuration.py
sib_api_v3_sdk/rest.py
sib_api_v3_sdk/api/__init__.py
sib_api_v3_sdk/api/account_api.py
sib_api_v3_sdk/api/attributes_api.py
sib_api_v3_sdk/api/contacts_api.py
sib_api_v3_sdk/api/email_campaigns_api.py
sib_api_v3_sdk/api/folders_api.py
sib_api_v3_sdk/api/inbound_parsing_api.py
sib_api_v3_sdk/api/lists_api.py
sib_api_v3_sdk/api/master_account_api.py
sib_api_v3_sdk/api/process_api.py
sib_api_v3_sdk/api/reseller_api.py
sib_api_v3_sdk/api/senders_api.py
sib_api_v3_sdk/api/sms_campaigns_api.py
sib_api_v3_sdk/api/transactional_emails_api.py
sib_api_v3_sdk/api/transactional_sms_api.py
sib_api_v3_sdk/api/webhooks_api.py
sib_api_v3_sdk/models/__init__.py
sib_api_v3_sdk/models/ab_test_campaign_result.py
sib_api_v3_sdk/models/ab_test_campaign_result_clicked_links.py
sib_api_v3_sdk/models/ab_test_campaign_result_statistics.py
sib_api_v3_sdk/models/ab_test_version_clicks.py
sib_api_v3_sdk/models/ab_test_version_clicks_inner.py
sib_api_v3_sdk/models/ab_test_version_stats.py
sib_api_v3_sdk/models/add_child_domain.py
sib_api_v3_sdk/models/add_contact_to_list.py
sib_api_v3_sdk/models/add_credits.py
sib_api_v3_sdk/models/block_domain.py
sib_api_v3_sdk/models/create_attribute.py
sib_api_v3_sdk/models/create_attribute_enumeration.py
sib_api_v3_sdk/models/create_child.py
sib_api_v3_sdk/models/create_contact.py
sib_api_v3_sdk/models/create_doi_contact.py
sib_api_v3_sdk/models/create_email_campaign.py
sib_api_v3_sdk/models/create_email_campaign_recipients.py
sib_api_v3_sdk/models/create_email_campaign_sender.py
sib_api_v3_sdk/models/create_list.py
sib_api_v3_sdk/models/create_model.py
sib_api_v3_sdk/models/create_reseller.py
sib_api_v3_sdk/models/create_sender.py
sib_api_v3_sdk/models/create_sender_ips.py
sib_api_v3_sdk/models/create_sender_model.py
sib_api_v3_sdk/models/create_sms_campaign.py
sib_api_v3_sdk/models/create_sms_campaign_recipients.py
sib_api_v3_sdk_mukulsib.egg-info/PKG-INFO
sib_api_v3_sdk_mukulsib.egg-info/SOURCES.txt
sib_api_v3_sdk_mukulsib.egg-info/dependency_links.txt
sib_api_v3_sdk_mukulsib.egg-info/requires.txt
sib_api_v3_sdk_mukulsib.egg-info/top_level.txt
