Metadata-Version: 1.0
Name: sib-api-v3-sdk-mukulsib
Version: 7.3.0
Summary: SendinBlue API
Home-page: UNKNOWN
Author: UNKNOWN
Author-email: contact@sendinblue.com
License: UNKNOWN
Keywords: Swagger,SendinBlue API
Platform: UNKNOWN
